pyanywhere/__init__.py
pyanywhere/consoles.py
pyanywhere/exceptions.py
pyanywhere/users.py
pyanywhere-0.0.0.dist-info/LICENSE
pyanywhere-0.0.0.dist-info/METADATA
pyanywhere-0.0.0.dist-info/WHEEL
pyanywhere-0.0.0.dist-info/top_level.txt
pyanywhere-0.0.0.dist-info/RECORD
