Metadata-Version: 2.1
Name: pyanywhere
Version: 0.0.0
Summary: Wrapper around the PythonAnywhere API with classes for consoles, webapps, etc.
Home-page: https://github.com/dullbananas/pyanywhere
Author: Dull Bananas
Author-email: dull.bananas0@gmail.com
License: MIT
Platform: UNKNOWN
Classifier: Development Status :: 3 - Alpha
Classifier: Intended Audience :: Developers
Classifier: License :: OSI Approved :: MIT License
Classifier: Programming Language :: Python :: 3
Classifier: Programming Language :: Python :: 3.6
Classifier: Programming Language :: Python :: 3.7
Classifier: Programming Language :: Python :: 3.8
Classifier: Programming Language :: Python :: 3 :: Only
Classifier: Topic :: Internet
Classifier: Topic :: Software Development :: Libraries :: Python Modules
Requires-Python: >=3.6
Requires-Dist: requests
